{
  "updated": "2026-04-23T14:05:38.836Z",
  "prices": {
    "eurusd": {
      "price": 1.16913,
      "chgPct": -0.015
    },
    "gbpusd": {
      "price": 1.34947,
      "chgPct": -0.044
    },
    "usdjpy": {
      "price": 159.58675,
      "chgPct": 0.007
    },
    "usdcad": {
      "price": 1.36854,
      "chgPct": 0.023
    },
    "usdchf": {
      "price": 0.78557,
      "chgPct": 0.006
    },
    "xauusd": {
      "price": 4722.83324,
      "chgPct": -0.093
    },
    "euraud": {
      "price": 1.63578,
      "chgPct": 0.007
    },
    "audusd": {
      "price": 0.71473,
      "chgPct": -0.024
    }
  }
}